Pcolors/__init__.py
Pcolors/__main__.py
Pcolors/exceptions.py
Pcolors/style.py
Pcolors/_functions/__init__.py
Pcolors/_functions/code.py
Pcolors/_functions/preview.py
Pcolors/_functions/prints.py
Pcolors/shorcuts/__init__.py
Pcolors/shorcuts/dark.py
Pcolors/shorcuts/format.py
Pcolors/shorcuts/light.py
Pcolors/shortcuts/__init__.py
Pcolors/shortcuts/dark.py
Pcolors/shortcuts/format.py
Pcolors/shortcuts/light.py
Pcolors-0.1.dist-info/LICENSE
Pcolors-0.1.dist-info/METADATA
Pcolors-0.1.dist-info/WHEEL
Pcolors-0.1.dist-info/top_level.txt
Pcolors-0.1.dist-info/RECORD
