Metadata-Version: 2.1
Name: Pcolors
Version: 0.1
Summary: Package to simplify printing colors in the console.
Home-page: https://github.com/rafalou38/Pcolors
Author: rafalou38
Author-email: rafaloulou2@gmail.com
License: UNKNOWN
Platform: UNKNOWN
Classifier: Programming Language :: Python :: 3
Classifier: License :: OSI Approved :: MIT License
Classifier: Operating System :: OS Independent
Classifier: Topic :: Printing
Requires-Python: >=3.6
